issuudl/__init__.py
issuudl/issuudl.py
issuudl_saperoi-0.2.1.dist-info/LICENSE
issuudl_saperoi-0.2.1.dist-info/METADATA
issuudl_saperoi-0.2.1.dist-info/WHEEL
issuudl_saperoi-0.2.1.dist-info/top_level.txt
issuudl_saperoi-0.2.1.dist-info/RECORD
