Metadata-Version: 2.1
Name: issuudl-saperoi
Version: 0.2.1
Summary: A python-based individual page downloader for Issuu.
Home-page: https://github.com/saperoi/issuudl-py
Author: Saperoi
Author-email: uesugi.sapero@gmail.com
License: UNKNOWN
Project-URL: Bug Tracker, https://github.com/saperoi/issuudl-py/issues
Platform: UNKNOWN
Classifier: Programming Language :: Python :: 3
Classifier: Operating System :: OS Independent
Classifier: License :: OSI Approved :: GNU General Public License v3 (GPLv3)
Requires-Python: >=3.6
License-File: LICENSE
